django_auth_exchange_organizations/VERSION_STAMP
django_auth_exchange_organizations/__init__.py
django_auth_exchange_organizations/admin.py
django_auth_exchange_organizations/apps.py
django_auth_exchange_organizations/models.py
django_auth_exchange_organizations/settings.py
django_auth_exchange_organizations/urls.py
django_auth_exchange_organizations/version.py
django_auth_exchange_organizations/wsgi.py
django_auth_exchange_organizations/migrations/0001_initial.py
django_auth_exchange_organizations/migrations/__init__.py
django_auth_exchange_organizations-0.1.3.dist-info/LICENSE
django_auth_exchange_organizations-0.1.3.dist-info/METADATA
django_auth_exchange_organizations-0.1.3.dist-info/WHEEL
django_auth_exchange_organizations-0.1.3.dist-info/top_level.txt
django_auth_exchange_organizations-0.1.3.dist-info/RECORD
