Metadata-Version: 2.1
Name: django-auth-exchange-organizations
Version: 0.1.3
Summary: A Django extension to django-auth-exchange that adds organization associations.
Home-page: https://github.com/gregschmit/django-auth-exchange-organizations
Author: Gregory N. Schmit
Author-email: gschmi4@uic.edu
License: MIT
Platform: UNKNOWN
Classifier: Environment :: Web Environment
Classifier: Framework :: Django
Classifier: Framework :: Django :: 2.0
Classifier: Intended Audience :: Developers
Classifier: License :: OSI Approved :: MIT License
Classifier: Operating System :: OS Independent
Classifier: Programming Language :: Python
Classifier: Programming Language :: Python :: 3.5
Classifier: Programming Language :: Python :: 3.6
Classifier: Topic :: Internet :: WWW/HTTP
Requires-Dist: Django (>=2)
Requires-Dist: django-auth-exchange
Requires-Dist: django-organizations
